hotmix/__init__.py
hotmix/exceptions.py
hotmix/main.py
hotmix-0.0.4.dist-info/METADATA
hotmix-0.0.4.dist-info/WHEEL
hotmix-0.0.4.dist-info/RECORD
