Metadata-Version: 2.1
Name: hotmix
Version: 0.0.4
Summary: Add htmx to your FastAPI application
License: LGPL-3.0-only
Author: flokapi
Author-email: flokapi@pm.me
Requires-Python: >=3.7,<4.0
Classifier: License :: OSI Approved :: GNU Lesser General Public License v3 (LGPLv3)
Classifier: Programming Language :: Python :: 3
Classifier: Programming Language :: Python :: 3.7
Classifier: Programming Language :: Python :: 3.8
Classifier: Programming Language :: Python :: 3.9
Classifier: Programming Language :: Python :: 3.10
Classifier: Programming Language :: Python :: 3.11
Classifier: Programming Language :: Python :: 3.12
Requires-Dist: fastapi
Project-URL: documentation, https://github.com/flokapi/hotmix
Project-URL: homepage, https://github.com/flokapi/hotmix
Project-URL: repository, https://github.com/flokapi/hotmix
